orangecanvas/__init__.py
orangecanvas/__main__.py
orangecanvas/config.py
orangecanvas/i18n_config.py
orangecanvas/main.py
orangecanvas/resources.py
orangecanvas/application/__init__.py
orangecanvas/application/aboutdialog.py
orangecanvas/application/addons.py
orangecanvas/application/application.py
orangecanvas/application/canvasmain.py
orangecanvas/application/canvastooldock.py
orangecanvas/application/examples.py
orangecanvas/application/outputview.py
orangecanvas/application/schemeinfo.py
orangecanvas/application/settings.py
orangecanvas/application/welcomedialog.py
orangecanvas/application/widgettoolbox.py
orangecanvas/application/tests/__init__.py
orangecanvas/application/tests/test_addons.py
orangecanvas/application/tests/test_addons_utils.py
orangecanvas/application/tests/test_application.py
orangecanvas/application/tests/test_canvastooldock.py
orangecanvas/application/tests/test_main.py
orangecanvas/application/tests/test_mainwindow.py
orangecanvas/application/tests/test_outputview.py
orangecanvas/application/tests/test_schemeinfo.py
orangecanvas/application/tests/test_settings.py
orangecanvas/application/tests/test_welcomedialog.py
orangecanvas/application/tests/test_widgettoolbox.py
orangecanvas/application/utils/__init__.py
orangecanvas/application/utils/addons.py
orangecanvas/canvas/__init__.py
orangecanvas/canvas/layout.py
orangecanvas/canvas/scene.py
orangecanvas/canvas/view.py
orangecanvas/canvas/items/__init__.py
orangecanvas/canvas/items/annotationitem.py
orangecanvas/canvas/items/controlpoints.py
orangecanvas/canvas/items/graphicspathobject.py
orangecanvas/canvas/items/graphicstextitem.py
orangecanvas/canvas/items/linkitem.py
orangecanvas/canvas/items/nodeitem.py
orangecanvas/canvas/items/utils.py
orangecanvas/canvas/items/tests/__init__.py
orangecanvas/canvas/items/tests/test_annotationitem.py
orangecanvas/canvas/items/tests/test_controlpoints.py
orangecanvas/canvas/items/tests/test_graphicspathobject.py
Blauwal3_Canvas_Core-0.2.4.dist-info/LICENSE.txt
Blauwal3_Canvas_Core-0.2.4.dist-info/METADATA
Blauwal3_Canvas_Core-0.2.4.dist-info/WHEEL
Blauwal3_Canvas_Core-0.2.4.dist-info/top_level.txt
Blauwal3_Canvas_Core-0.2.4.dist-info/RECORD
